torcpy/__init__.py
torcpy/runtime.py
torcpy-0.1.1.dist-info/LICENSE
torcpy-0.1.1.dist-info/METADATA
torcpy-0.1.1.dist-info/WHEEL
torcpy-0.1.1.dist-info/top_level.txt
torcpy-0.1.1.dist-info/RECORD
