Metadata-Version: 2.1
Name: torcpy
Version: 0.1.1
Summary: TORC Tasking library
Home-page: http://github.com/ibm/torc_py/
Author: Panagiotis Chatzidoukas
Author-email: phadjido@gmail.com
License: Eclipse Public License v1.0
Platform: UNKNOWN
Classifier: Programming Language :: Python :: 3
Classifier: License :: OSI Approved
Classifier: Operating System :: OS Independent
Requires-Dist: mpi4py
Requires-Dist: numpy
Requires-Dist: termcolor
Requires-Dist: cma
Requires-Dist: pillow
Requires-Dist: coloredlogs
Requires-Dist: pytest
